bids_mosaic-0.1.0.dist-info/licenses/LICENSE.txt
bidsmosaic/__init__.py
bidsmosaic/mosaic.py
bids_mosaic-0.1.0.dist-info/METADATA
bids_mosaic-0.1.0.dist-info/WHEEL
bids_mosaic-0.1.0.dist-info/entry_points.txt
bids_mosaic-0.1.0.dist-info/top_level.txt
bids_mosaic-0.1.0.dist-info/RECORD
